ato/__init__.py
ato/adict.py
ato/parser.py
ato/scope.py
ato/trace.py
ato/utils.py
ato/xyz.py
ato/db_routers/__init__.py
ato/db_routers/sql/__init__.py
ato/db_routers/sql/manager.py
ato/db_routers/sql/schema.py
ato/hyperopt/__init__.py
ato/hyperopt/base.py
ato/hyperopt/hyperband.py
ato-2.1.7.dist-info/licenses/LICENSE
ato-2.1.7.dist-info/METADATA
ato-2.1.7.dist-info/WHEEL
ato-2.1.7.dist-info/top_level.txt
ato-2.1.7.dist-info/RECORD
