Metadata-Version: 2.4
Name: ato
Version: 2.1.7
Summary: Configuration, experimentation, and hyperparameter optimization for Python. No runtime magic. No launcher. Just Python modules you compose.
Author: ato contributors
License: MIT
Project-URL: Homepage, https://github.com/yourusername/ato
Project-URL: Repository, https://github.com/yourusername/ato
Project-URL: Documentation, https://github.com/yourusername/ato#readme
Project-URL: Issues, https://github.com/yourusername/ato/issues
Keywords: config management,experiment tracking,hyperparameter optimization,lightweight,composable,namespace isolation,machine learning
Classifier: Development Status :: 4 - Beta
Classifier: Intended Audience :: Developers
Classifier: Intended Audience :: Science/Research
Classifier: License :: OSI Approved :: MIT License
Classifier: Programming Language :: Python :: 3
Classifier: Programming Language :: Python :: 3.7
Classifier: Programming Language :: Python :: 3.8
Classifier: Programming Language :: Python :: 3.9
Classifier: Programming Language :: Python :: 3.10
Classifier: Programming Language :: Python :: 3.11
Classifier: Topic :: Scientific/Engineering :: Artificial Intelligence
Classifier: Topic :: Software Development :: Libraries :: Python Modules
Requires-Python: >=3.7
License-File: LICENSE
Requires-Dist: pyyaml>=6.0
Requires-Dist: toml>=0.10.2
Requires-Dist: sqlalchemy>=2.0
Requires-Dist: numpy>=1.19.0
Provides-Extra: distributed
Requires-Dist: torch>=1.8.0; extra == "distributed"
Dynamic: license-file
